pyminion/__init__.py
pyminion/core.py
pyminion/decisions.py
pyminion/exceptions.py
pyminion/game.py
pyminion/players.py
pyminion/result.py
pyminion/simulator.py
pyminion/bots/__init__.py
pyminion/bots/bot.py
pyminion/bots/optimized_bot.py
pyminion/bots/examples/__init__.py
pyminion/bots/examples/bandit_bot.py
pyminion/bots/examples/big_money.py
pyminion/bots/examples/big_money_smithy.py
pyminion/bots/examples/big_money_ultimate.py
pyminion/bots/examples/chapel_bot.py
pyminion/expansions/__init__.py
pyminion/expansions/base.py
pyminion/expansions/intrigue.py
pyminion/expansions/seaside.py
pyminion-0.3.0.dist-info/LICENSE
pyminion-0.3.0.dist-info/METADATA
pyminion-0.3.0.dist-info/WHEEL
pyminion-0.3.0.dist-info/top_level.txt
pyminion-0.3.0.dist-info/RECORD
