Metadata-Version: 2.1
Name: pyminion
Version: 0.3.0
Summary: Dominion but make it python
Home-page: https://github.com/evanofslack/pyminion
Author: Evan Slack
Author-email: evan.slack@outlook.com
Classifier: Programming Language :: Python :: 3
Classifier: License :: OSI Approved :: MIT License
Classifier: Operating System :: OS Independent
Requires-Python: >=3.8
License-File: LICENSE
